treedb/__init__.py
treedb/_globals.py
treedb/_proxies.py
treedb/_tools.py
treedb/checks.py
treedb/config.py
treedb/export.py
treedb/glottolog.py
treedb/import_models.py
treedb/logging_.py
treedb/models.py
treedb/queries.py
treedb/settings.py
treedb/backend/__init__.py
treedb/backend/_basics.py
treedb/backend/export.py
treedb/backend/load.py
treedb/backend/models.py
treedb/backend/pandas.py
treedb/backend/sqlite_master.py
treedb/backend/views.py
treedb/languoids/__init__.py
treedb/languoids/_root.py
treedb/languoids/fields.py
treedb/languoids/files.py
treedb/languoids/records.py
treedb/raw/__init__.py
treedb/raw/export.py
treedb/raw/import_models.py
treedb/raw/models.py
treedb/raw/records.py
treedb-2.7.1.dist-info/licenses/LICENSE.txt
treedb-2.7.1.dist-info/METADATA
treedb-2.7.1.dist-info/WHEEL
treedb-2.7.1.dist-info/top_level.txt
treedb-2.7.1.dist-info/RECORD
