Metadata-Version: 2.4
Name: treedb
Version: 2.7.1
Summary: Glottolog languoid tree as SQLite database
Author-email: Sebastian Bank <sebastian.bank@uni-leipzig.de>
License-Expression: MIT
Project-URL: Homepage, https://github.com/glottolog/treedb
Project-URL: Changelog, https://github.com/glottolog/treedb/blob/master/CHANGES.rst
Project-URL: Issue Tracker, https://github.com/glottolog/treedb/issues
Project-URL: CI, https://github.com/glottolog/treedb/actions
Project-URL: Coverage, https://codecov.io/gh/glottolog/treedb
Keywords: glottolog,languoids,sqlite3,database
Platform: any
Classifier: Development Status :: 5 - Production/Stable
Classifier: Intended Audience :: Developers
Classifier: Intended Audience :: Science/Research
Classifier: Operating System :: OS Independent
Classifier: Programming Language :: Python :: 3
Classifier: Programming Language :: Python :: 3.9
Classifier: Programming Language :: Python :: 3.10
Classifier: Programming Language :: Python :: 3.11
Classifier: Programming Language :: Python :: 3.12
Classifier: Programming Language :: Python :: 3.13
Requires-Python: >=3.9
License-File: LICENSE.txt
Requires-Dist: csv23~=0.3
Requires-Dist: pycountry==24.6.1
Requires-Dist: sqlalchemy>=1.4.24
Provides-Extra: dev
Requires-Dist: build; extra == "dev"
Requires-Dist: wheel; extra == "dev"
Requires-Dist: twine; extra == "dev"
Requires-Dist: flake8; extra == "dev"
Requires-Dist: Flake8-pyproject; extra == "dev"
Requires-Dist: pep8-naming; extra == "dev"
Requires-Dist: tox>=3; extra == "dev"
Provides-Extra: test
Requires-Dist: pytest>=6; extra == "test"
Requires-Dist: pytest-cov; extra == "test"
Requires-Dist: coverage; extra == "test"
Provides-Extra: pretty
Requires-Dist: sqlparse>=0.3; extra == "pretty"
Provides-Extra: pandas
Requires-Dist: pandas>=1; extra == "pandas"
Dynamic: license-file
